git_writing/__init__.py
git_writing/build.py
git_writing/init_repo.py
git_writing/assets/csl/chicago-fullnote-bibliography-short-title-subsequent.csl
git_writing/assets/templates/article/authors.yaml
git_writing/assets/templates/article/style.yaml
git_writing/assets/templates/article/template.tex
git_writing/assets/templates/article/text.md
git_writing-0.0.1.dev1.dist-info/LICENSE
git_writing-0.0.1.dev1.dist-info/METADATA
git_writing-0.0.1.dev1.dist-info/WHEEL
git_writing-0.0.1.dev1.dist-info/entry_points.txt
git_writing-0.0.1.dev1.dist-info/top_level.txt
git_writing-0.0.1.dev1.dist-info/RECORD
