Metadata-Version: 2.1
Name: git-writing
Version: 0.0.1-dev1
Summary: Accomplishes a number of the tedious, tedious tasks associated with reproducible and version-controlled academic writing.
Home-page: https://gitlab.com/ericrobskyhuntley/git-writing
Author: Eric Robsky Huntley
Author-email: ehuntley@mit.edu
License: GNU General Public License v3 (GPLv3)
Project-URL: Bug Tracker, https://gitlab.com/ericrobskyhuntley/git-writing/-/issues
Keywords: pandoc,zotero,plaintext,writing,git
Platform: UNKNOWN
Classifier: Programming Language :: Python :: 3
Classifier: License :: OSI Approved :: GNU General Public License v3 (GPLv3)
Classifier: Operating System :: OS Independent
Requires-Python: >=3.6
License-File: LICENSE
Requires-Dist: GitPython (>=3.1.18)
Requires-Dist: pypandoc (>=1.5)
Requires-Dist: Pyzotero (>=1.4.24)
